candle_llm-0.2.6.dist-info/METADATA
candle_llm-0.2.6.dist-info/WHEEL
candle_llm/__init__.py
candle_llm/_core.cpython-312-darwin.so
candle_llm-0.2.6.dist-info/RECORD
