Metadata-Version: 2.4
Name: candle-llm
Version: 0.2.6
Classifier: Programming Language :: Rust
Classifier: Programming Language :: Python :: Implementation :: CPython
Classifier: Programming Language :: Python :: Implementation :: PyPy
Summary: data represent, processing
Author-email: wangmengdi <790990241@qq.com>
Requires-Python: >=3.8
